viet_text_tools/__init__.py
viet_text_tools/tests/test_things.py
viet_text_tools-0.1.6.dist-info/LICENSE
viet_text_tools-0.1.6.dist-info/WHEEL
viet_text_tools-0.1.6.dist-info/METADATA
viet_text_tools-0.1.6.dist-info/RECORD
