Metadata-Version: 2.1
Name: viet-text-tools
Version: 0.1.6
Summary: Functions for working with Vietnamese text
Home-page: https://github.com/enricobarzetti/viet_text_tools
License: MIT
Author: Enrico Barzetti
Author-email: enricobarzetti@gmail.com
Requires-Python: >=3.8,<4.0
Classifier: License :: OSI Approved :: MIT License
Classifier: Programming Language :: Python :: 3
Classifier: Programming Language :: Python :: 3.8
